shapefile.py
pyshp-3.0.2.post0.dist-info/METADATA
pyshp-3.0.2.post0.dist-info/WHEEL
pyshp-3.0.2.post0.dist-info/licenses/LICENSE.TXT
pyshp-3.0.2.post0.dist-info/RECORD
