Metadata-Version: 2.4
Name: pyshp
Version: 3.0.2.post0
Summary: Pure Python read/write support for ESRI Shapefile format
Project-URL: Repository, https://github.com/GeospatialPython/pyshp
Author-email: Joel Lawhead <jlawhead@geospatialpython.com>
Maintainer-email: Karim Bahgat <karim.bahgat.norway@gmail.com>
License-Expression: MIT
License-File: LICENSE.TXT
Keywords: geographic,geospatial,gis,shapefile,shapefiles
Classifier: Development Status :: 5 - Production/Stable
Classifier: Programming Language :: Python
Classifier: Programming Language :: Python :: 3
Classifier: Programming Language :: Python :: 3 :: Only
Classifier: Topic :: Scientific/Engineering :: GIS
Classifier: Topic :: Software Development :: Libraries
Classifier: Topic :: Software Development :: Libraries :: Python Modules
Requires-Python: >=3.9
Provides-Extra: dev
Requires-Dist: pre-commit; extra == 'dev'
Requires-Dist: pytest; extra == 'dev'
Requires-Dist: ruff; extra == 'dev'
Provides-Extra: test
Requires-Dist: pytest; extra == 'test'
